zbmain/__init__.py
zbmain/datasets/__init__.py
zbmain/datasets/dataset.py
zbmain/losses/__init__.py
zbmain/models/__init__.py
zbmain/models/tf_gru.py
zbmain/optimizers/__init__.py
zbmain/utils/__init__.py
zbmain/utils/args.py
zbmain/utils/config.py
zbmain/utils/file.py
zbmain/utils/onehot.py
zbmain/utils/path.py
zbmain/utils/rebot.py
zbmain/utils/string.py
zbmain/utils/time.py
zbmain/utils/tools.py
zbmain/utils/translate.py
zbAI-0.0.1.dist-info/LICENSE
zbAI-0.0.1.dist-info/METADATA
zbAI-0.0.1.dist-info/WHEEL
zbAI-0.0.1.dist-info/top_level.txt
zbAI-0.0.1.dist-info/RECORD
